README.md
setup.py
deepdictiterator/__init__.py
deepdictiterator.egg-info/PKG-INFO
deepdictiterator.egg-info/SOURCES.txt
deepdictiterator.egg-info/dependency_links.txt
deepdictiterator.egg-info/top_level.txt