Metadata-Version: 2.1
Name: deepdictiterator
Version: 0.0.1
Summary: Iterates through deep dictionaries
Home-page: https://github.com/pashazz/deepdictiterator
Author: Pavel Borisov
Author-email: pzinin@gmail.com
License: UNKNOWN
Platform: UNKNOWN
Classifier: Programming Language :: Python :: 3
Classifier: License :: OSI Approved :: Apache Software License
Classifier: Operating System :: OS Independent
Classifier: Development Status :: 2 - Pre-Alpha
